cli_command_parser/__init__.py
cli_command_parser/__main__.py
cli_command_parser/__version__.py
cli_command_parser/annotations.py
cli_command_parser/command_parameters.py
cli_command_parser/commands.py
cli_command_parser/compat.py
cli_command_parser/config.py
cli_command_parser/context.py
cli_command_parser/core.py
cli_command_parser/documentation.py
cli_command_parser/exceptions.py
cli_command_parser/metadata.py
cli_command_parser/nargs.py
cli_command_parser/parse_tree.py
cli_command_parser/parser.py
cli_command_parser/testing.py
cli_command_parser/typing.py
cli_command_parser/utils.py
cli_command_parser/conversion/__init__.py
cli_command_parser/conversion/__main__.py
cli_command_parser/conversion/argparse_ast.py
cli_command_parser/conversion/argparse_utils.py
cli_command_parser/conversion/cli.py
cli_command_parser/conversion/command_builder.py
cli_command_parser/conversion/utils.py
cli_command_parser/conversion/visitor.py
cli_command_parser/error_handling/__init__.py
cli_command_parser/error_handling/base.py
cli_command_parser/error_handling/other.py
cli_command_parser/error_handling/windows.py
cli_command_parser/formatting/__init__.py
cli_command_parser/formatting/commands.py
cli_command_parser/formatting/params.py
cli_command_parser/formatting/restructured_text.py
cli_command_parser/formatting/utils.py
cli_command_parser/inputs/__init__.py
cli_command_parser/inputs/base.py
cli_command_parser/inputs/choices.py
cli_command_parser/inputs/exceptions.py
cli_command_parser/inputs/files.py
cli_command_parser/inputs/numeric.py
cli_command_parser/inputs/patterns.py
cli_command_parser/inputs/time.py
cli_command_parser/inputs/utils.py
cli_command_parser/parameters/__init__.py
cli_command_parser/parameters/actions.py
cli_command_parser/parameters/base.py
cli_command_parser/parameters/choice_map.py
cli_command_parser/parameters/groups.py
cli_command_parser/parameters/option_strings.py
cli_command_parser/parameters/options.py
cli_command_parser/parameters/pass_thru.py
cli_command_parser-2026.2.1.dist-info/licenses/LICENSE
cli_command_parser-2026.2.1.dist-info/METADATA
cli_command_parser-2026.2.1.dist-info/WHEEL
cli_command_parser-2026.2.1.dist-info/entry_points.txt
cli_command_parser-2026.2.1.dist-info/top_level.txt
cli_command_parser-2026.2.1.dist-info/RECORD
