Metadata-Version: 2.4
Name: cli_command_parser
Version: 2026.2.1
Summary: CLI Command Parser
Author-email: Doug Skrypa <dskrypa@gmail.com>
Project-URL: Source, https://github.com/dskrypa/cli_command_parser
Project-URL: Documentation, https://dskrypa.github.io/cli_command_parser
Project-URL: Issues, https://github.com/dskrypa/cli_command_parser/issues
Classifier: Development Status :: 5 - Production/Stable
Classifier: Environment :: Console
Classifier: Intended Audience :: Developers
Classifier: License :: OSI Approved :: Apache Software License
Classifier: Operating System :: OS Independent
Classifier: Programming Language :: Python
Classifier: Programming Language :: Python :: 3
Classifier: Programming Language :: Python :: 3.10
Classifier: Programming Language :: Python :: 3.11
Classifier: Programming Language :: Python :: 3.12
Classifier: Programming Language :: Python :: 3.13
Classifier: Programming Language :: Python :: 3.14
Classifier: Topic :: Software Development :: User Interfaces
Classifier: Topic :: Text Processing
Requires-Python: >=3.10
License-File: LICENSE
Provides-Extra: wcwidth
Requires-Dist: wcwidth; extra == "wcwidth"
Dynamic: license-file
